{
    "foundationStartingSize": 7,
    "wastepileCardsToShow": 3,
    "nonTopXOffset": 0.25,
    "draggedTokenOffset": 0.5,
    "cardsToDeal": 3,
	"cardsToReactorspeed": 15,
    "relativeCardScale": 0.12,
    "turnsTillReset": 18,
    "matchPoints": 200,
    "emptyReactorPoint": 1000,
    "perfectGamePoints": 2800,
    "delayToShowGameSummary": 2,
    "easyReactorLimit": 24,
    "mediumReactorLimit": 21,
    "hardReactorLimit": 18,
    "easyMoveCount": 24,
    "mediumMoveCount": 21,
    "hardMoveCount": 18,
    "selectedCardOpacity": 0.25,
    "cardHighlightColor": [ 0.5, 0.5, 1, 1 ],
    "turnAlertSmallThreshold": 10,
    "turnAlertThreshold": 5,

    "gameStateTxtEnglish": [ "You Won!", "You Lost..." ],
    "menuSceneButtonsTxtEnglish": [ "Play", "Tutorial", "Credits" ],
    "loadingSceneTxtEnglish": "Loading",
    "levelSceneButtonsTxtEnglish": [ "Easy", "Medium", "Hard", "Return" ],
    "pauseSceneButtonsTxtEnglish": [ "Resume", "Restart", "Settings", "Main Menu" ],
    "summarySceneButtonsTxtEnglish": [ "Main\n Menu", "Play\n Again" ],
    "scoreActionLabelsTxtEnglish": [ "Score", "Action" ]
}
